jetson_stats_sender/__init__.py
jetson_stats_sender/http_service.py
jetson_stats_sender-0.1.dist-info/METADATA
jetson_stats_sender-0.1.dist-info/WHEEL
jetson_stats_sender-0.1.dist-info/top_level.txt
jetson_stats_sender-0.1.dist-info/RECORD
