Metadata-Version: 2.1
Name: jetson-stats-sender
Version: 0.1
Summary: Communication interface to talk to the projet_jetson web-server
Home-page: http://github.com/loriko/jetson_stats_sender
Author: Loriko
Author-email: fmahe058@uottawa.ca
License: MIT
Platform: UNKNOWN
